{
  "posts": [],
  "users": [
    {
      "fname": "David",
      "lname": "Moyer",
      "username": "SoftRainbowBoi",
      "email": "poinky_m@hotmail.com",
      "following": [],
      "liked": [],
      "password": "$2a$10$zNooZPMTIuhAU33bBVCLtel7GChRehHav5jiTK8VlHmN/PgzxcZ6C",
      "id": 1,
      "imageURL": "https://tse1.mm.bing.net/th?id=OIP.0pVwpLhb1hwpINZ07iODeQHaFj&pid=Api&P=0&w=235&h=177",
      "alerts": []
    },
    {
      "fname": "Test",
      "lname": "User",
      "username": "TestUser",
      "email": "test@test.com",
      "following": [],
      "liked": [],
      "password": "$2a$10$36a9iPdrDXcVpqwU.szWnuHNklAfnvYzCs69o7gkj4xKih2HRlY2S",
      "id": 2,
      "alerts": []
    }
  ]
}